CHANGELOG.md
sk_transformers/__init__.py
sk_transformers/base_transformer.py
sk_transformers/datetime_transformer.py
sk_transformers/encoder_transformer.py
sk_transformers/generic_transformer.py
sk_transformers/number_transformer.py
sk_transformers/string_transformer.py
sk_transformers/utils.py
sk_transformers-0.11.0.dist-info/LICENSE
sk_transformers-0.11.0.dist-info/WHEEL
sk_transformers-0.11.0.dist-info/METADATA
sk_transformers-0.11.0.dist-info/RECORD
