Metadata-Version: 2.1
Name: sk-transformers
Version: 0.11.0
Summary: A collection of various pandas & scikit-learn compatible transformers for all kinds of preprocessing and feature engineering
Home-page: https://chrislemke.github.io/sk-transformers/
License: MIT
Keywords: feature engineering,preprocessing,pandas,scikit-learn,transformer,pipelines,machine learning,data science,artificial intelligence
Author: Christopher Lemke
Author-email: 1@lemke.ai
Requires-Python: >=3.8,<3.12
Classifier: Intended Audience :: Science/Research
Classifier: License :: OSI Approved :: MIT License
Classifier: Natural Language :: English
Classifier: Programming Language :: Python :: 3
Classifier: Programming Language :: Python :: 3.8
Classifier: Programming Language :: Python :: 3.9
Classifier: Programming Language :: Python :: 3.10
Classifier: Programming Language :: Python :: 3.11
Classifier: Topic :: Scientific/Engineering :: Artificial Intelligence
Classifier: Topic :: Scientific/Engineering :: Information Analysis
Classifier: Topic :: Software Development :: Pre-processors
Classifier: Typing :: Typed
Requires-Dist: feature-engine (>=1.5.2,<2.0.0)
Requires-Dist: ipywidgets (>=8.0.4,<9.0.0)
Requires-Dist: joblib (==1.2.0)
Requires-Dist: numpy (==1.23.5)
Requires-Dist: pandas (>=1.5.2,<2.0.0)
Requires-Dist: phonenumbers (>=8.13.4,<9.0.0)
Requires-Dist: polars (>=0.16.7,<0.17.0)
Requires-Dist: pyarrow (>=11.0.0,<12.0.0)
Requires-Dist: rich (>=13.3.1,<14.0.0)
Requires-Dist: scikit-learn (>=1.2.0,<2.0.0)
Project-URL: Changelog, https://github.com/chrislemke/sk-transformers/blob/main/CHANGELOG.md
Project-URL: Contributing, https://github.com/chrislemke/sk-transformers/blob/main/docs/CONTRIBUTING.md
Project-URL: Documentation, https://chrislemke.github.io/sk-transformers/
Project-URL: Discussions, https://github.com/chrislemke/sk-transformers/discussions
Project-URL: Issues, https://github.com/chrislemke/sk-transformers/issues
Project-URL: Repository, https://github.com/chrislemke/sk-transformers/
